{
  "user_34ea7db3": [
    {
      "file_hash": "ef79ecf41801693a2dff149e669e81ff14682b916d6c49ecb3f0b72b0cc49e5f",
      "file_name": "BNTAS_20910.pdf",
      "file_path": "temp\\BNTAS_20910.pdf",
      "processed_at": "2025-08-17T02:45:03.361946",
      "vector_collection_name": "user_34ea7db3_b9668b50",
      "document_metadata": {
        "file_name": "BNTAS_20910.pdf",
        "file_path": "C:\\Users\\belyi\\Desktop\\dataneuron\\temp\\BNTAS_20910.pdf",
        "file_type": ".pdf",
        "file_size_mb": 0.013,
        "creation_date": "2025-08-17T02:45:01.905257",
        "modification_date": "2025-08-17T02:45:01.906244",
        "page_count": 2,
        "character_count": 1554,
        "word_count": 210,
        "pdf_title": "",
        "pdf_author": "",
        "pdf_subject": "",
        "pdf_creator": ""
      },
      "file_size_mb": 0.013276100158691406,
      "content_preview": "SÜREKLİ BİLGİLERE İLİŞKİN ÖZEL DURUM AÇIKLAMASI\nKonu     Pay Alım Beyanı:\nYapılan Açıklama Düzeltme mi?     HAYIR:\nBildirime Konu Borsa Şirketi     BANTAŞ BANDIRMA AMBALAJ SANAYİ TİCARET A.Ş.:\nAçıklam"
    },
    {
      "file_hash": "d8d804fc25c3edde49df4c26b72b721f3313e2b6eb1280696e56d60a61ec121f",
      "file_name": "Project Proposal Statement New.pdf",
      "file_path": "temp\\Project Proposal Statement New.pdf",
      "processed_at": "2025-08-17T02:45:05.878778",
      "vector_collection_name": "user_34ea7db3_27ff3e16",
      "document_metadata": {
        "file_name": "Project Proposal Statement New.pdf",
        "file_path": "C:\\Users\\belyi\\Desktop\\dataneuron\\temp\\Project Proposal Statement New.pdf",
        "file_type": ".pdf",
        "file_size_mb": 0.181,
        "creation_date": "2025-08-17T02:45:03.372326",
        "modification_date": "2025-08-17T02:45:03.372745",
        "page_count": 5,
        "character_count": 5112,
        "word_count": 735,
        "pdf_title": "",
        "pdf_author": "Alper Özcan",
        "pdf_subject": "",
        "pdf_creator": "Microsoft® Word Microsoft 365 için"
      },
      "file_size_mb": 0.1813068389892578,
      "content_preview": "Full-Stack E -Commerce Web Application & Admin Portal  \nCourse: CSE 214 Advanced Application Development  \nProject Title: Full-Stack E -Commerce Web Application Development  \n \nObjective  \nThe objecti"
    }
  ],
  "user_690132dc": [
    {
      "file_hash": "ef79ecf41801693a2dff149e669e81ff14682b916d6c49ecb3f0b72b0cc49e5f",
      "file_name": "BNTAS_20910.pdf",
      "file_path": "temp\\BNTAS_20910.pdf",
      "processed_at": "2025-08-17T03:04:10.199677",
      "vector_collection_name": "user_690132dc_b9668b50",
      "document_metadata": {
        "file_name": "BNTAS_20910.pdf",
        "file_path": "C:\\Users\\belyi\\Desktop\\dataneuron\\temp\\BNTAS_20910.pdf",
        "file_type": ".pdf",
        "file_size_mb": 0.013,
        "creation_date": "2025-08-17T03:04:08.951648",
        "modification_date": "2025-08-17T03:04:08.952585",
        "page_count": 2,
        "character_count": 1554,
        "word_count": 210,
        "pdf_title": "",
        "pdf_author": "",
        "pdf_subject": "",
        "pdf_creator": ""
      },
      "file_size_mb": 0.013276100158691406,
      "content_preview": "SÜREKLİ BİLGİLERE İLİŞKİN ÖZEL DURUM AÇIKLAMASI\nKonu     Pay Alım Beyanı:\nYapılan Açıklama Düzeltme mi?     HAYIR:\nBildirime Konu Borsa Şirketi     BANTAŞ BANDIRMA AMBALAJ SANAYİ TİCARET A.Ş.:\nAçıklam"
    },
    {
      "file_hash": "d8d804fc25c3edde49df4c26b72b721f3313e2b6eb1280696e56d60a61ec121f",
      "file_name": "Project Proposal Statement New.pdf",
      "file_path": "temp\\Project Proposal Statement New.pdf",
      "processed_at": "2025-08-17T03:04:11.487946",
      "vector_collection_name": "user_690132dc_27ff3e16",
      "document_metadata": {
        "file_name": "Project Proposal Statement New.pdf",
        "file_path": "C:\\Users\\belyi\\Desktop\\dataneuron\\temp\\Project Proposal Statement New.pdf",
        "file_type": ".pdf",
        "file_size_mb": 0.181,
        "creation_date": "2025-08-17T03:04:10.209736",
        "modification_date": "2025-08-17T03:04:10.210236",
        "page_count": 5,
        "character_count": 5112,
        "word_count": 735,
        "pdf_title": "",
        "pdf_author": "Alper Özcan",
        "pdf_subject": "",
        "pdf_creator": "Microsoft® Word Microsoft 365 için"
      },
      "file_size_mb": 0.1813068389892578,
      "content_preview": "Full-Stack E -Commerce Web Application & Admin Portal  \nCourse: CSE 214 Advanced Application Development  \nProject Title: Full-Stack E -Commerce Web Application Development  \n \nObjective  \nThe objecti"
    }
  ],
  "user_856926da": [
    {
      "file_hash": "ef79ecf41801693a2dff149e669e81ff14682b916d6c49ecb3f0b72b0cc49e5f",
      "file_name": "BNTAS_20910.pdf",
      "file_path": "temp\\BNTAS_20910.pdf",
      "processed_at": "2025-08-17T03:22:14.752115",
      "vector_collection_name": "user_856926da_b9668b50",
      "document_metadata": {
        "file_name": "BNTAS_20910.pdf",
        "file_path": "C:\\Users\\belyi\\Desktop\\dataneuron\\temp\\BNTAS_20910.pdf",
        "file_type": ".pdf",
        "file_size_mb": 0.013,
        "creation_date": "2025-08-17T03:22:13.216726",
        "modification_date": "2025-08-17T03:22:13.217737",
        "page_count": 2,
        "character_count": 1554,
        "word_count": 210,
        "pdf_title": "",
        "pdf_author": "",
        "pdf_subject": "",
        "pdf_creator": ""
      },
      "file_size_mb": 0.013276100158691406,
      "content_preview": "SÜREKLİ BİLGİLERE İLİŞKİN ÖZEL DURUM AÇIKLAMASI\nKonu     Pay Alım Beyanı:\nYapılan Açıklama Düzeltme mi?     HAYIR:\nBildirime Konu Borsa Şirketi     BANTAŞ BANDIRMA AMBALAJ SANAYİ TİCARET A.Ş.:\nAçıklam"
    },
    {
      "file_hash": "d8d804fc25c3edde49df4c26b72b721f3313e2b6eb1280696e56d60a61ec121f",
      "file_name": "Project Proposal Statement New.pdf",
      "file_path": "temp\\Project Proposal Statement New.pdf",
      "processed_at": "2025-08-17T03:22:17.217125",
      "vector_collection_name": "user_856926da_27ff3e16",
      "document_metadata": {
        "file_name": "Project Proposal Statement New.pdf",
        "file_path": "C:\\Users\\belyi\\Desktop\\dataneuron\\temp\\Project Proposal Statement New.pdf",
        "file_type": ".pdf",
        "file_size_mb": 0.181,
        "creation_date": "2025-08-17T03:22:14.777931",
        "modification_date": "2025-08-17T03:22:14.778518",
        "page_count": 5,
        "character_count": 5112,
        "word_count": 735,
        "pdf_title": "",
        "pdf_author": "Alper Özcan",
        "pdf_subject": "",
        "pdf_creator": "Microsoft® Word Microsoft 365 için"
      },
      "file_size_mb": 0.1813068389892578,
      "content_preview": "Full-Stack E -Commerce Web Application & Admin Portal  \nCourse: CSE 214 Advanced Application Development  \nProject Title: Full-Stack E -Commerce Web Application Development  \n \nObjective  \nThe objecti"
    }
  ],
  "user_aa9d3745": [
    {
      "file_hash": "ef79ecf41801693a2dff149e669e81ff14682b916d6c49ecb3f0b72b0cc49e5f",
      "file_name": "BNTAS_20910.pdf",
      "file_path": "temp\\BNTAS_20910.pdf",
      "processed_at": "2025-08-17T03:31:54.223011",
      "vector_collection_name": "user_aa9d3745_b9668b50",
      "document_metadata": {
        "file_name": "BNTAS_20910.pdf",
        "file_path": "C:\\Users\\belyi\\Desktop\\dataneuron\\temp\\BNTAS_20910.pdf",
        "file_type": ".pdf",
        "file_size_mb": 0.013,
        "creation_date": "2025-08-17T03:31:52.455648",
        "modification_date": "2025-08-17T03:31:52.456462",
        "page_count": 2,
        "character_count": 1554,
        "word_count": 210,
        "pdf_title": "",
        "pdf_author": "",
        "pdf_subject": "",
        "pdf_creator": ""
      },
      "file_size_mb": 0.013276100158691406,
      "content_preview": "SÜREKLİ BİLGİLERE İLİŞKİN ÖZEL DURUM AÇIKLAMASI\nKonu     Pay Alım Beyanı:\nYapılan Açıklama Düzeltme mi?     HAYIR:\nBildirime Konu Borsa Şirketi     BANTAŞ BANDIRMA AMBALAJ SANAYİ TİCARET A.Ş.:\nAçıklam"
    },
    {
      "file_hash": "d8d804fc25c3edde49df4c26b72b721f3313e2b6eb1280696e56d60a61ec121f",
      "file_name": "Project Proposal Statement New.pdf",
      "file_path": "temp\\Project Proposal Statement New.pdf",
      "processed_at": "2025-08-17T03:31:56.758847",
      "vector_collection_name": "user_aa9d3745_27ff3e16",
      "document_metadata": {
        "file_name": "Project Proposal Statement New.pdf",
        "file_path": "C:\\Users\\belyi\\Desktop\\dataneuron\\temp\\Project Proposal Statement New.pdf",
        "file_type": ".pdf",
        "file_size_mb": 0.181,
        "creation_date": "2025-08-17T03:31:54.232881",
        "modification_date": "2025-08-17T03:31:54.233744",
        "page_count": 5,
        "character_count": 5112,
        "word_count": 735,
        "pdf_title": "",
        "pdf_author": "Alper Özcan",
        "pdf_subject": "",
        "pdf_creator": "Microsoft® Word Microsoft 365 için"
      },
      "file_size_mb": 0.1813068389892578,
      "content_preview": "Full-Stack E -Commerce Web Application & Admin Portal  \nCourse: CSE 214 Advanced Application Development  \nProject Title: Full-Stack E -Commerce Web Application Development  \n \nObjective  \nThe objecti"
    }
  ],
  "user_4985b8c9": [
    {
      "file_hash": "ef79ecf41801693a2dff149e669e81ff14682b916d6c49ecb3f0b72b0cc49e5f",
      "file_name": "BNTAS_20910.pdf",
      "file_path": "temp\\BNTAS_20910.pdf",
      "processed_at": "2025-08-17T03:41:10.206738",
      "vector_collection_name": "user_4985b8c9_b9668b50",
      "document_metadata": {
        "file_name": "BNTAS_20910.pdf",
        "file_path": "C:\\Users\\belyi\\Desktop\\dataneuron\\temp\\BNTAS_20910.pdf",
        "file_type": ".pdf",
        "file_size_mb": 0.013,
        "creation_date": "2025-08-17T03:41:08.809830",
        "modification_date": "2025-08-17T03:41:08.811383",
        "page_count": 2,
        "character_count": 1554,
        "word_count": 210,
        "pdf_title": "",
        "pdf_author": "",
        "pdf_subject": "",
        "pdf_creator": ""
      },
      "file_size_mb": 0.013276100158691406,
      "content_preview": "SÜREKLİ BİLGİLERE İLİŞKİN ÖZEL DURUM AÇIKLAMASI\nKonu     Pay Alım Beyanı:\nYapılan Açıklama Düzeltme mi?     HAYIR:\nBildirime Konu Borsa Şirketi     BANTAŞ BANDIRMA AMBALAJ SANAYİ TİCARET A.Ş.:\nAçıklam"
    }
  ],
  "user_68189324": [
    {
      "file_hash": "d8d804fc25c3edde49df4c26b72b721f3313e2b6eb1280696e56d60a61ec121f",
      "file_name": "Project Proposal Statement New.pdf",
      "file_path": "temp\\Project Proposal Statement New.pdf",
      "processed_at": "2025-08-17T03:51:04.627823",
      "vector_collection_name": "user_68189324_27ff3e16",
      "document_metadata": {
        "file_name": "Project Proposal Statement New.pdf",
        "file_path": "C:\\Users\\belyi\\Desktop\\dataneuron\\temp\\Project Proposal Statement New.pdf",
        "file_type": ".pdf",
        "file_size_mb": 0.181,
        "creation_date": "2025-08-17T03:51:02.824815",
        "modification_date": "2025-08-17T03:51:02.825777",
        "page_count": 5,
        "character_count": 5112,
        "word_count": 735,
        "pdf_title": "",
        "pdf_author": "Alper Özcan",
        "pdf_subject": "",
        "pdf_creator": "Microsoft® Word Microsoft 365 için"
      },
      "file_size_mb": 0.1813068389892578,
      "content_preview": "Full-Stack E -Commerce Web Application & Admin Portal  \nCourse: CSE 214 Advanced Application Development  \nProject Title: Full-Stack E -Commerce Web Application Development  \n \nObjective  \nThe objecti"
    }
  ],
  "user_3be457f7": [
    {
      "file_hash": "d8d804fc25c3edde49df4c26b72b721f3313e2b6eb1280696e56d60a61ec121f",
      "file_name": "Project Proposal Statement New.pdf",
      "file_path": "temp\\Project Proposal Statement New.pdf",
      "processed_at": "2025-08-17T03:53:25.392663",
      "vector_collection_name": "user_3be457f7_27ff3e16",
      "document_metadata": {
        "file_name": "Project Proposal Statement New.pdf",
        "file_path": "C:\\Users\\belyi\\Desktop\\dataneuron\\temp\\Project Proposal Statement New.pdf",
        "file_type": ".pdf",
        "file_size_mb": 0.181,
        "creation_date": "2025-08-17T03:53:23.808530",
        "modification_date": "2025-08-17T03:53:23.809589",
        "page_count": 5,
        "character_count": 5112,
        "word_count": 735,
        "pdf_title": "",
        "pdf_author": "Alper Özcan",
        "pdf_subject": "",
        "pdf_creator": "Microsoft® Word Microsoft 365 için"
      },
      "file_size_mb": 0.1813068389892578,
      "content_preview": "Full-Stack E -Commerce Web Application & Admin Portal  \nCourse: CSE 214 Advanced Application Development  \nProject Title: Full-Stack E -Commerce Web Application Development  \n \nObjective  \nThe objecti"
    }
  ],
  "user_710acf24": [
    {
      "file_hash": "ef79ecf41801693a2dff149e669e81ff14682b916d6c49ecb3f0b72b0cc49e5f",
      "file_name": "BNTAS_20910.pdf",
      "file_path": "temp\\BNTAS_20910.pdf",
      "processed_at": "2025-08-19T15:27:31.547109",
      "vector_collection_name": "user_710acf24_b9668b50",
      "document_metadata": {
        "file_name": "BNTAS_20910.pdf",
        "file_path": "C:\\Users\\belyi\\Desktop\\dataneuron\\temp\\BNTAS_20910.pdf",
        "file_type": ".pdf",
        "file_size_mb": 0.013,
        "creation_date": "2025-08-19T15:27:29.962615",
        "modification_date": "2025-08-19T15:27:29.962615",
        "page_count": 2,
        "character_count": 1554,
        "word_count": 210,
        "pdf_title": "",
        "pdf_author": "",
        "pdf_subject": "",
        "pdf_creator": ""
      },
      "file_size_mb": 0.013276100158691406,
      "content_preview": "SÜREKLİ BİLGİLERE İLİŞKİN ÖZEL DURUM AÇIKLAMASI\nKonu     Pay Alım Beyanı:\nYapılan Açıklama Düzeltme mi?     HAYIR:\nBildirime Konu Borsa Şirketi     BANTAŞ BANDIRMA AMBALAJ SANAYİ TİCARET A.Ş.:\nAçıklam"
    }
  ],
  "user_1c27a1c8": [
    {
      "file_hash": "ef79ecf41801693a2dff149e669e81ff14682b916d6c49ecb3f0b72b0cc49e5f",
      "file_name": "BNTAS_20910.pdf",
      "file_path": "C:\\Users\\belyi\\Desktop\\dataneuron\\uploads\\user_1c27a1c8\\BNTAS_20910.pdf",
      "processed_at": "2025-08-19T15:47:40.298858",
      "vector_collection_name": "user_1c27a1c8_b9668b50",
      "document_metadata": {
        "file_name": "BNTAS_20910.pdf",
        "file_path": "C:\\Users\\belyi\\Desktop\\dataneuron\\uploads\\user_1c27a1c8\\BNTAS_20910.pdf",
        "file_type": ".pdf",
        "file_size_mb": 0.013,
        "creation_date": "2025-08-19T15:47:38.110380",
        "modification_date": "2025-08-19T15:47:38.110380",
        "page_count": 2,
        "character_count": 1554,
        "word_count": 210,
        "pdf_title": "",
        "pdf_author": "",
        "pdf_subject": "",
        "pdf_creator": ""
      },
      "file_size_mb": 0.013276100158691406,
      "content_preview": "SÜREKLİ BİLGİLERE İLİŞKİN ÖZEL DURUM AÇIKLAMASI\nKonu     Pay Alım Beyanı:\nYapılan Açıklama Düzeltme mi?     HAYIR:\nBildirime Konu Borsa Şirketi     BANTAŞ BANDIRMA AMBALAJ SANAYİ TİCARET A.Ş.:\nAçıklam"
    },
    {
      "file_hash": "d8d804fc25c3edde49df4c26b72b721f3313e2b6eb1280696e56d60a61ec121f",
      "file_name": "Project Proposal Statement New.pdf",
      "file_path": "C:\\Users\\belyi\\Desktop\\dataneuron\\uploads\\user_1c27a1c8\\Project Proposal Statement New.pdf",
      "processed_at": "2025-08-19T15:48:49.509942",
      "vector_collection_name": "user_1c27a1c8_27ff3e16",
      "document_metadata": {
        "file_name": "Project Proposal Statement New.pdf",
        "file_path": "C:\\Users\\belyi\\Desktop\\dataneuron\\uploads\\user_1c27a1c8\\Project Proposal Statement New.pdf",
        "file_type": ".pdf",
        "file_size_mb": 0.181,
        "creation_date": "2025-08-19T15:48:47.443966",
        "modification_date": "2025-08-19T15:48:47.447463",
        "page_count": 5,
        "character_count": 5112,
        "word_count": 735,
        "pdf_title": "",
        "pdf_author": "Alper Özcan",
        "pdf_subject": "",
        "pdf_creator": "Microsoft® Word Microsoft 365 için"
      },
      "file_size_mb": 0.1813068389892578,
      "content_preview": "Full-Stack E -Commerce Web Application & Admin Portal  \nCourse: CSE 214 Advanced Application Development  \nProject Title: Full-Stack E -Commerce Web Application Development  \n \nObjective  \nThe objecti"
    }
  ],
  "user_30795938": [
    {
      "file_hash": "d8d804fc25c3edde49df4c26b72b721f3313e2b6eb1280696e56d60a61ec121f",
      "file_name": "Project Proposal Statement New.pdf",
      "file_path": "C:\\Users\\belyi\\Desktop\\dataneuron\\uploads\\user_30795938\\Project Proposal Statement New.pdf",
      "processed_at": "2025-08-19T16:03:08.600118",
      "vector_collection_name": "user_30795938_27ff3e16",
      "document_metadata": {
        "file_name": "Project Proposal Statement New.pdf",
        "file_path": "C:\\Users\\belyi\\Desktop\\dataneuron\\uploads\\user_30795938\\Project Proposal Statement New.pdf",
        "file_type": ".pdf",
        "file_size_mb": 0.181,
        "creation_date": "2025-08-19T16:03:06.585356",
        "modification_date": "2025-08-19T16:03:06.588923",
        "page_count": 5,
        "character_count": 5112,
        "word_count": 735,
        "pdf_title": "",
        "pdf_author": "Alper Özcan",
        "pdf_subject": "",
        "pdf_creator": "Microsoft® Word Microsoft 365 için"
      },
      "file_size_mb": 0.1813068389892578,
      "content_preview": "Full-Stack E -Commerce Web Application & Admin Portal  \nCourse: CSE 214 Advanced Application Development  \nProject Title: Full-Stack E -Commerce Web Application Development  \n \nObjective  \nThe objecti"
    }
  ],
  "user_c3cb440b": [
    {
      "file_hash": "d8d804fc25c3edde49df4c26b72b721f3313e2b6eb1280696e56d60a61ec121f",
      "file_name": "Project Proposal Statement New.pdf",
      "file_path": "C:\\Users\\belyi\\Desktop\\dataneuron\\uploads\\user_c3cb440b\\Project Proposal Statement New.pdf",
      "processed_at": "2025-08-19T16:12:30.948520",
      "vector_collection_name": "user_c3cb440b_27ff3e16",
      "document_metadata": {
        "file_name": "Project Proposal Statement New.pdf",
        "file_path": "C:\\Users\\belyi\\Desktop\\dataneuron\\uploads\\user_c3cb440b\\Project Proposal Statement New.pdf",
        "file_type": ".pdf",
        "file_size_mb": 0.181,
        "creation_date": "2025-08-19T16:12:29.060685",
        "modification_date": "2025-08-19T16:12:29.063181",
        "page_count": 5,
        "character_count": 5112,
        "word_count": 735,
        "pdf_title": "",
        "pdf_author": "Alper Özcan",
        "pdf_subject": "",
        "pdf_creator": "Microsoft® Word Microsoft 365 için"
      },
      "file_size_mb": 0.1813068389892578,
      "content_preview": "Full-Stack E -Commerce Web Application & Admin Portal  \nCourse: CSE 214 Advanced Application Development  \nProject Title: Full-Stack E -Commerce Web Application Development  \n \nObjective  \nThe objecti"
    }
  ],
  "user_133dff9f": [
    {
      "file_hash": "d8d804fc25c3edde49df4c26b72b721f3313e2b6eb1280696e56d60a61ec121f",
      "file_name": "Project Proposal Statement New.pdf",
      "file_path": "C:\\Users\\belyi\\Desktop\\dataneuron\\uploads\\user_133dff9f\\Project Proposal Statement New.pdf",
      "processed_at": "2025-08-19T16:20:31.455479",
      "vector_collection_name": "user_133dff9f_27ff3e16",
      "document_metadata": {
        "file_name": "Project Proposal Statement New.pdf",
        "file_path": "C:\\Users\\belyi\\Desktop\\dataneuron\\uploads\\user_133dff9f\\Project Proposal Statement New.pdf",
        "file_type": ".pdf",
        "file_size_mb": 0.181,
        "creation_date": "2025-08-19T16:20:29.160847",
        "modification_date": "2025-08-19T16:20:29.162538",
        "page_count": 5,
        "character_count": 5112,
        "word_count": 735,
        "pdf_title": "",
        "pdf_author": "Alper Özcan",
        "pdf_subject": "",
        "pdf_creator": "Microsoft® Word Microsoft 365 için"
      },
      "file_size_mb": 0.1813068389892578,
      "content_preview": "Full-Stack E -Commerce Web Application & Admin Portal  \nCourse: CSE 214 Advanced Application Development  \nProject Title: Full-Stack E -Commerce Web Application Development  \n \nObjective  \nThe objecti"
    }
  ],
  "user_59eb6e62": [
    {
      "file_hash": "d8d804fc25c3edde49df4c26b72b721f3313e2b6eb1280696e56d60a61ec121f",
      "file_name": "Project Proposal Statement New.pdf",
      "file_path": "C:\\Users\\belyi\\Desktop\\dataneuron\\uploads\\user_59eb6e62\\Project Proposal Statement New.pdf",
      "processed_at": "2025-08-19T16:29:40.962949",
      "vector_collection_name": "user_59eb6e62_27ff3e16",
      "document_metadata": {
        "file_name": "Project Proposal Statement New.pdf",
        "file_path": "C:\\Users\\belyi\\Desktop\\dataneuron\\uploads\\user_59eb6e62\\Project Proposal Statement New.pdf",
        "file_type": ".pdf",
        "file_size_mb": 0.181,
        "creation_date": "2025-08-19T16:29:39.727489",
        "modification_date": "2025-08-19T16:29:39.729086",
        "page_count": 5,
        "character_count": 5112,
        "word_count": 735,
        "pdf_title": "",
        "pdf_author": "Alper Özcan",
        "pdf_subject": "",
        "pdf_creator": "Microsoft® Word Microsoft 365 için"
      },
      "file_size_mb": 0.1813068389892578,
      "content_preview": "Full-Stack E -Commerce Web Application & Admin Portal  \nCourse: CSE 214 Advanced Application Development  \nProject Title: Full-Stack E -Commerce Web Application Development  \n \nObjective  \nThe objecti"
    }
  ],
  "user_509d1323": [
    {
      "file_hash": "d8d804fc25c3edde49df4c26b72b721f3313e2b6eb1280696e56d60a61ec121f",
      "file_name": "Project Proposal Statement New.pdf",
      "file_path": "C:\\Users\\belyi\\Desktop\\dataneuron\\uploads\\user_509d1323\\Project Proposal Statement New.pdf",
      "processed_at": "2025-08-19T17:25:22.003945",
      "vector_collection_name": "user_509d1323_27ff3e16",
      "document_metadata": {
        "file_name": "Project Proposal Statement New.pdf",
        "file_path": "C:\\Users\\belyi\\Desktop\\dataneuron\\uploads\\user_509d1323\\Project Proposal Statement New.pdf",
        "file_type": ".pdf",
        "file_size_mb": 0.181,
        "creation_date": "2025-08-19T17:25:20.522035",
        "modification_date": "2025-08-19T17:25:20.523810",
        "page_count": 5,
        "character_count": 5112,
        "word_count": 735,
        "pdf_title": "",
        "pdf_author": "Alper Özcan",
        "pdf_subject": "",
        "pdf_creator": "Microsoft® Word Microsoft 365 için"
      },
      "file_size_mb": 0.1813068389892578,
      "content_preview": "Full-Stack E -Commerce Web Application & Admin Portal  \nCourse: CSE 214 Advanced Application Development  \nProject Title: Full-Stack E -Commerce Web Application Development  \n \nObjective  \nThe objecti"
    }
  ],
  "user_efe685a1": [
    {
      "file_hash": "d8d804fc25c3edde49df4c26b72b721f3313e2b6eb1280696e56d60a61ec121f",
      "file_name": "Project Proposal Statement New.pdf",
      "file_path": "C:\\Users\\belyi\\Desktop\\dataneuron\\uploads\\user_efe685a1\\Project Proposal Statement New.pdf",
      "processed_at": "2025-08-19T17:29:36.373667",
      "vector_collection_name": "user_efe685a1_27ff3e16",
      "document_metadata": {
        "file_name": "Project Proposal Statement New.pdf",
        "file_path": "C:\\Users\\belyi\\Desktop\\dataneuron\\uploads\\user_efe685a1\\Project Proposal Statement New.pdf",
        "file_type": ".pdf",
        "file_size_mb": 0.181,
        "creation_date": "2025-08-19T17:29:33.977510",
        "modification_date": "2025-08-19T17:29:33.980404",
        "page_count": 5,
        "character_count": 5112,
        "word_count": 735,
        "pdf_title": "",
        "pdf_author": "Alper Özcan",
        "pdf_subject": "",
        "pdf_creator": "Microsoft® Word Microsoft 365 için"
      },
      "file_size_mb": 0.1813068389892578,
      "content_preview": "Full-Stack E -Commerce Web Application & Admin Portal  \nCourse: CSE 214 Advanced Application Development  \nProject Title: Full-Stack E -Commerce Web Application Development  \n \nObjective  \nThe objecti"
    }
  ],
  "user_8f054bc2": [
    {
      "file_hash": "d8d804fc25c3edde49df4c26b72b721f3313e2b6eb1280696e56d60a61ec121f",
      "file_name": "Project Proposal Statement New.pdf",
      "file_path": "C:\\Users\\belyi\\Desktop\\dataneuron\\uploads\\user_8f054bc2\\Project Proposal Statement New.pdf",
      "processed_at": "2025-08-19T17:36:28.036825",
      "vector_collection_name": "user_8f054bc2_27ff3e16",
      "document_metadata": {
        "file_name": "Project Proposal Statement New.pdf",
        "file_path": "C:\\Users\\belyi\\Desktop\\dataneuron\\uploads\\user_8f054bc2\\Project Proposal Statement New.pdf",
        "file_type": ".pdf",
        "file_size_mb": 0.181,
        "creation_date": "2025-08-19T17:36:24.624010",
        "modification_date": "2025-08-19T17:36:24.625431",
        "page_count": 5,
        "character_count": 5112,
        "word_count": 735,
        "pdf_title": "",
        "pdf_author": "Alper Özcan",
        "pdf_subject": "",
        "pdf_creator": "Microsoft® Word Microsoft 365 için"
      },
      "file_size_mb": 0.1813068389892578,
      "content_preview": "Full-Stack E -Commerce Web Application & Admin Portal  \nCourse: CSE 214 Advanced Application Development  \nProject Title: Full-Stack E -Commerce Web Application Development  \n \nObjective  \nThe objecti"
    }
  ],
  "user_73ea3ff4": [
    {
      "file_hash": "d8d804fc25c3edde49df4c26b72b721f3313e2b6eb1280696e56d60a61ec121f",
      "file_name": "Project Proposal Statement New.pdf",
      "file_path": "C:\\Users\\belyi\\Desktop\\dataneuron\\uploads\\user_73ea3ff4\\Project Proposal Statement New.pdf",
      "processed_at": "2025-08-19T17:56:30.301968",
      "vector_collection_name": "user_73ea3ff4_27ff3e16",
      "document_metadata": {
        "file_name": "Project Proposal Statement New.pdf",
        "file_path": "C:\\Users\\belyi\\Desktop\\dataneuron\\uploads\\user_73ea3ff4\\Project Proposal Statement New.pdf",
        "file_type": ".pdf",
        "file_size_mb": 0.181,
        "creation_date": "2025-08-19T17:56:28.367080",
        "modification_date": "2025-08-19T17:56:28.370268",
        "page_count": 5,
        "character_count": 5112,
        "word_count": 735,
        "pdf_title": "",
        "pdf_author": "Alper Özcan",
        "pdf_subject": "",
        "pdf_creator": "Microsoft® Word Microsoft 365 için"
      },
      "file_size_mb": 0.1813068389892578,
      "content_preview": "Full-Stack E -Commerce Web Application & Admin Portal  \nCourse: CSE 214 Advanced Application Development  \nProject Title: Full-Stack E -Commerce Web Application Development  \n \nObjective  \nThe objecti"
    }
  ],
  "user_7b7ba594": [
    {
      "file_hash": "d8d804fc25c3edde49df4c26b72b721f3313e2b6eb1280696e56d60a61ec121f",
      "file_name": "Project Proposal Statement New.pdf",
      "file_path": "C:\\Users\\belyi\\Desktop\\dataneuron\\uploads\\user_7b7ba594\\Project Proposal Statement New.pdf",
      "processed_at": "2025-08-19T17:57:30.488550",
      "vector_collection_name": "user_7b7ba594_27ff3e16",
      "document_metadata": {
        "file_name": "Project Proposal Statement New.pdf",
        "file_path": "C:\\Users\\belyi\\Desktop\\dataneuron\\uploads\\user_7b7ba594\\Project Proposal Statement New.pdf",
        "file_type": ".pdf",
        "file_size_mb": 0.181,
        "creation_date": "2025-08-19T17:57:28.725391",
        "modification_date": "2025-08-19T17:57:28.727083",
        "page_count": 5,
        "character_count": 5112,
        "word_count": 735,
        "pdf_title": "",
        "pdf_author": "Alper Özcan",
        "pdf_subject": "",
        "pdf_creator": "Microsoft® Word Microsoft 365 için"
      },
      "file_size_mb": 0.1813068389892578,
      "content_preview": "Full-Stack E -Commerce Web Application & Admin Portal  \nCourse: CSE 214 Advanced Application Development  \nProject Title: Full-Stack E -Commerce Web Application Development  \n \nObjective  \nThe objecti"
    }
  ],
  "user_a4965a14": [
    {
      "file_hash": "d8d804fc25c3edde49df4c26b72b721f3313e2b6eb1280696e56d60a61ec121f",
      "file_name": "Project Proposal Statement New.pdf",
      "file_path": "C:\\Users\\belyi\\Desktop\\dataneuron\\uploads\\user_a4965a14\\Project Proposal Statement New.pdf",
      "processed_at": "2025-08-19T18:22:43.349122",
      "vector_collection_name": "user_a4965a14_27ff3e16",
      "document_metadata": {
        "file_name": "Project Proposal Statement New.pdf",
        "file_path": "C:\\Users\\belyi\\Desktop\\dataneuron\\uploads\\user_a4965a14\\Project Proposal Statement New.pdf",
        "file_type": ".pdf",
        "file_size_mb": 0.181,
        "creation_date": "2025-08-19T18:22:41.454351",
        "modification_date": "2025-08-19T18:22:41.455953",
        "page_count": 5,
        "character_count": 5112,
        "word_count": 735,
        "pdf_title": "",
        "pdf_author": "Alper Özcan",
        "pdf_subject": "",
        "pdf_creator": "Microsoft® Word Microsoft 365 için"
      },
      "file_size_mb": 0.1813068389892578,
      "content_preview": "Full-Stack E -Commerce Web Application & Admin Portal  \nCourse: CSE 214 Advanced Application Development  \nProject Title: Full-Stack E -Commerce Web Application Development  \n \nObjective  \nThe objecti"
    }
  ],
  "user_6f6f39a1": [
    {
      "file_hash": "d8d804fc25c3edde49df4c26b72b721f3313e2b6eb1280696e56d60a61ec121f",
      "file_name": "Project Proposal Statement New.pdf",
      "file_path": "C:\\Users\\belyi\\Desktop\\dataneuron\\uploads\\user_6f6f39a1\\Project Proposal Statement New.pdf",
      "processed_at": "2025-08-19T19:18:56.445119",
      "vector_collection_name": "user_6f6f39a1_27ff3e16",
      "document_metadata": {
        "file_name": "Project Proposal Statement New.pdf",
        "file_path": "C:\\Users\\belyi\\Desktop\\dataneuron\\uploads\\user_6f6f39a1\\Project Proposal Statement New.pdf",
        "file_type": ".pdf",
        "file_size_mb": 0.181,
        "creation_date": "2025-08-19T19:18:54.741282",
        "modification_date": "2025-08-19T19:18:54.742947",
        "page_count": 5,
        "character_count": 5112,
        "word_count": 735,
        "pdf_title": "",
        "pdf_author": "Alper Özcan",
        "pdf_subject": "",
        "pdf_creator": "Microsoft® Word Microsoft 365 için"
      },
      "file_size_mb": 0.1813068389892578,
      "content_preview": "Full-Stack E -Commerce Web Application & Admin Portal  \nCourse: CSE 214 Advanced Application Development  \nProject Title: Full-Stack E -Commerce Web Application Development  \n \nObjective  \nThe objecti"
    }
  ],
  "user_dcef7b9b": [
    {
      "file_hash": "d8d804fc25c3edde49df4c26b72b721f3313e2b6eb1280696e56d60a61ec121f",
      "file_name": "Project Proposal Statement New.pdf",
      "file_path": "C:\\Users\\belyi\\Desktop\\dataneuron\\uploads\\user_dcef7b9b\\Project Proposal Statement New.pdf",
      "processed_at": "2025-08-19T19:44:45.359726",
      "vector_collection_name": "user_dcef7b9b_27ff3e16",
      "document_metadata": {
        "file_name": "Project Proposal Statement New.pdf",
        "file_path": "C:\\Users\\belyi\\Desktop\\dataneuron\\uploads\\user_dcef7b9b\\Project Proposal Statement New.pdf",
        "file_type": ".pdf",
        "file_size_mb": 0.181,
        "creation_date": "2025-08-19T19:44:43.580914",
        "modification_date": "2025-08-19T19:44:43.585037",
        "page_count": 5,
        "character_count": 5112,
        "word_count": 735,
        "pdf_title": "",
        "pdf_author": "Alper Özcan",
        "pdf_subject": "",
        "pdf_creator": "Microsoft® Word Microsoft 365 için"
      },
      "file_size_mb": 0.1813068389892578,
      "content_preview": "Full-Stack E -Commerce Web Application & Admin Portal  \nCourse: CSE 214 Advanced Application Development  \nProject Title: Full-Stack E -Commerce Web Application Development  \n \nObjective  \nThe objecti"
    }
  ],
  "user_b2126b10": [
    {
      "file_hash": "d8d804fc25c3edde49df4c26b72b721f3313e2b6eb1280696e56d60a61ec121f",
      "file_name": "Project Proposal Statement New.pdf",
      "file_path": "C:\\Users\\belyi\\Desktop\\dataneuron\\uploads\\user_b2126b10\\Project Proposal Statement New.pdf",
      "processed_at": "2025-08-19T21:22:14.737658",
      "vector_collection_name": "user_b2126b10_27ff3e16",
      "document_metadata": {
        "file_name": "Project Proposal Statement New.pdf",
        "file_path": "C:\\Users\\belyi\\Desktop\\dataneuron\\uploads\\user_b2126b10\\Project Proposal Statement New.pdf",
        "file_type": ".pdf",
        "file_size_mb": 0.181,
        "creation_date": "2025-08-19T21:22:12.461728",
        "modification_date": "2025-08-19T21:22:12.463107",
        "page_count": 5,
        "character_count": 5112,
        "word_count": 735,
        "pdf_title": "",
        "pdf_author": "Alper Özcan",
        "pdf_subject": "",
        "pdf_creator": "Microsoft® Word Microsoft 365 için"
      },
      "file_size_mb": 0.1813068389892578,
      "content_preview": "Full-Stack E -Commerce Web Application & Admin Portal  \nCourse: CSE 214 Advanced Application Development  \nProject Title: Full-Stack E -Commerce Web Application Development  \n \nObjective  \nThe objecti"
    }
  ],
  "user_e64bd8d6": [
    {
      "file_hash": "d8d804fc25c3edde49df4c26b72b721f3313e2b6eb1280696e56d60a61ec121f",
      "file_name": "Project Proposal Statement New.pdf",
      "file_path": "C:\\Users\\belyi\\Desktop\\dataneuron\\uploads\\user_e64bd8d6\\Project Proposal Statement New.pdf",
      "processed_at": "2025-08-19T21:33:55.828074",
      "vector_collection_name": "user_e64bd8d6_27ff3e16",
      "document_metadata": {
        "file_name": "Project Proposal Statement New.pdf",
        "file_path": "C:\\Users\\belyi\\Desktop\\dataneuron\\uploads\\user_e64bd8d6\\Project Proposal Statement New.pdf",
        "file_type": ".pdf",
        "file_size_mb": 0.181,
        "creation_date": "2025-08-19T21:33:53.725156",
        "modification_date": "2025-08-19T21:33:53.726886",
        "page_count": 5,
        "character_count": 5112,
        "word_count": 735,
        "pdf_title": "",
        "pdf_author": "Alper Özcan",
        "pdf_subject": "",
        "pdf_creator": "Microsoft® Word Microsoft 365 için"
      },
      "file_size_mb": 0.1813068389892578,
      "content_preview": "Full-Stack E -Commerce Web Application & Admin Portal  \nCourse: CSE 214 Advanced Application Development  \nProject Title: Full-Stack E -Commerce Web Application Development  \n \nObjective  \nThe objecti"
    }
  ]
}